.gitattributes
.gitignore
.travis.yml
LICENSE
LICENSE.spdx
README.md
README.rst
RELEASE
__coconut__.py
_config.yml
appveyor.yml
chardet.pyi
explorer-integration.bat
install.bat
install.sh
logo-small.png
run.bat
run.sh
setup.py
thunar-integration.py
thunar-integration.template
docs/CONTRIBUTING.md
docs/TUTORIAL.md
docs/fast-branching.pdf
docs/system-integration.md
docs/tutorial.ipynb
extras/difffile.sh
extras/logo.ico
extras/logo.png
extras/offline.sh
sos/__coconut__.py
sos/__init__.coco
sos/__init__.py
sos/__init__.pyi
sos/__main__.py
sos/pure.coco
sos/pure.py
sos/sos.coco
sos/sos.py
sos/tests.coco
sos/tests.py
sos/usage.coco
sos/usage.py
sos/utility.coco
sos/utility.py
sos/values.coco
sos/values.py
sos/version.py
sos/../LICENSE
sos/../LICENSE.spdx
sos/../README.md
sos/../README.rst
sos/../RELEASE
sos/../explorer-integration.bat
sos/../docs/CONTRIBUTING.md
sos/../docs/TUTORIAL.md
sos/../docs/funding.md
sos/../docs/system-integration.md
sos_vcs.egg-info/PKG-INFO
sos_vcs.egg-info/SOURCES.txt
sos_vcs.egg-info/dependency_links.txt
sos_vcs.egg-info/entry_points.txt
sos_vcs.egg-info/not-zip-safe
sos_vcs.egg-info/requires.txt
sos_vcs.egg-info/top_level.txt