Metadata-Version: 1.2
Name: sos-vcs
Version: 2020.1528.2201
Summary: Subversion Offline Solution (SOS)
Home-page: http://github.com/ArneBachmann/sos
Author: Arne Bachmann
Author-email: ArneBachmann@users.noreply.github.com
Maintainer: Arne Bachmann
Maintainer-email: ArneBachmann@users.noreply.github.com
License: MPL-2.0
Keywords: VCS SCM version control system Subversion Git gitless Fossil Bazaar Mercurial CVS SVN gl fsl bzr hg
Platform: UNKNOWN
Classifier: Development Status :: 5 - Production/Stable
Classifier: License :: Free To Use But Restricted
Classifier: Intended Audience :: Developers
Classifier: Intended Audience :: Other Audience
Classifier: Intended Audience :: Science/Research
Classifier: Intended Audience :: System Administrators
Classifier: License :: OSI Approved :: Mozilla Public License 2.0 (MPL 2.0)
Classifier: Operating System :: OS Independent
Classifier: Programming Language :: Other
Classifier: Programming Language :: Python
Classifier: Programming Language :: Python :: 3
Classifier: Programming Language :: Python :: 3.4
Classifier: Programming Language :: Python :: 3.5
Classifier: Programming Language :: Python :: 3.6
Classifier: Programming Language :: Python :: 3.7
Classifier: Programming Language :: Python :: 3 :: Only
Requires-Python: >=3.4
